Metadata-Version: 1.2
Name: gymbag
Version: 0.4.9
Summary: Simple efficient data recording for OpenAI Gym reinforcement learning environments
Home-page: https://gitlab.com/doctorj/gymbag
Author: Doctor J
Author-email: UNKNOWN
License: LGPL-3.0+
Keywords: reinforcement learning openai gym record storage binary hdf5
Platform: UNKNOWN
Classifier: Development Status :: 4 - Beta
Classifier: Intended Audience :: Developers
Classifier: Intended Audience :: Science/Research
Classifier: Topic :: Scientific/Engineering :: Artificial Intelligence
Classifier: License :: OSI Approved :: GNU Lesser General Public License v3 or later (LGPLv3+)
Classifier: Programming Language :: Python :: 3.4
Classifier: Programming Language :: Python :: 3.5
Classifier: Programming Language :: Python :: 3.6
Requires-Python: >=3.4
